guolei_py3_brhk/__init__.py
guolei_py3_brhk/speaker.py
guolei_py3_brhk/library/__init__.py
guolei_py3_brhk/library/spearker.py
guolei_py3_brhk-2.2.1.dist-info/LICENSE
guolei_py3_brhk-2.2.1.dist-info/METADATA
guolei_py3_brhk-2.2.1.dist-info/WHEEL
guolei_py3_brhk-2.2.1.dist-info/top_level.txt
guolei_py3_brhk-2.2.1.dist-info/RECORD
